{
    "key": "group_53baf202470d6",
    "title": "Team Details",
    "fields": [
        {
            "key": "field_5092f9178a383",
            "label": "Profile Photo",
            "name": "libtech_team_profile_photo",
            "type": "image",
            "instructions": "",
            "required": 0,
            "conditional_logic": 0,
            "wrapper": {
                "width": "",
                "class": "",
                "id": ""
            },
            "preview_size": "thumbnail",
            "library": "all",
            "return_format": "id",
            "min_width": 0,
            "min_height": 0,
            "min_size": 0,
            "max_width": 0,
            "max_height": 0,
            "max_size": 0,
            "mime_types": ""
        },
        {
            "key": "field_50aae23906d57",
            "label": "Profile Tagline",
            "name": "libtech_team_profile_tagline",
            "type": "text",
            "instructions": "Add a couple words describing the rider.",
            "required": 0,
            "conditional_logic": 0,
            "wrapper": {
                "width": "",
                "class": "",
                "id": ""
            },
            "default_value": "",
            "placeholder": "",
            "prepend": "",
            "append": "",
            "formatting": "none",
            "maxlength": "",
            "readonly": 0,
            "disabled": 0
        },
        {
            "key": "field_520d5eb794d46",
            "label": "Home",
            "name": "libtech_team_home",
            "type": "text",
            "instructions": "",
            "required": 0,
            "conditional_logic": 0,
            "wrapper": {
                "width": "",
                "class": "",
                "id": ""
            },
            "default_value": "",
            "placeholder": "",
            "prepend": "",
            "append": "",
            "formatting": "none",
            "maxlength": "",
            "readonly": 0,
            "disabled": 0
        },
        {
            "key": "field_520d5ec994d47",
            "label": "Sponsors",
            "name": "libtech_team_sponsors",
            "type": "text",
            "instructions": "",
            "required": 0,
            "conditional_logic": 0,
            "wrapper": {
                "width": "",
                "class": "",
                "id": ""
            },
            "default_value": "",
            "placeholder": "",
            "prepend": "",
            "append": "",
            "formatting": "none",
            "maxlength": "",
            "readonly": 0,
            "disabled": 0
        },
        {
            "key": "field_5092f91793fc1",
            "label": "Personal Website",
            "name": "libtech_team_personal_website",
            "type": "text",
            "instructions": "",
            "required": 0,
            "conditional_logic": 0,
            "wrapper": {
                "width": "",
                "class": "",
                "id": ""
            },
            "default_value": "",
            "placeholder": "",
            "prepend": "",
            "append": "",
            "formatting": "none",
            "maxlength": "",
            "readonly": 0,
            "disabled": 0
        },
        {
            "key": "field_5092f917966ec",
            "label": "Facebook Username",
            "name": "libtech_team_facebook_username",
            "type": "text",
            "instructions": "",
            "required": 0,
            "conditional_logic": 0,
            "wrapper": {
                "width": "",
                "class": "",
                "id": ""
            },
            "default_value": "",
            "placeholder": "",
            "prepend": "",
            "append": "",
            "formatting": "none",
            "maxlength": "",
            "readonly": 0,
            "disabled": 0
        },
        {
            "key": "field_5092f91798de7",
            "label": "Twitter Username",
            "name": "libtech_team_twitter_username",
            "type": "text",
            "instructions": "",
            "required": 0,
            "conditional_logic": 0,
            "wrapper": {
                "width": "",
                "class": "",
                "id": ""
            },
            "default_value": "",
            "placeholder": "",
            "prepend": "",
            "append": "",
            "formatting": "none",
            "maxlength": "",
            "readonly": 0,
            "disabled": 0
        },
        {
            "key": "field_5092f9179b503",
            "label": "Vimeo Username",
            "name": "libtech_team_vimeo_username",
            "type": "text",
            "instructions": "",
            "required": 0,
            "conditional_logic": 0,
            "wrapper": {
                "width": "",
                "class": "",
                "id": ""
            },
            "default_value": "",
            "placeholder": "",
            "prepend": "",
            "append": "",
            "formatting": "none",
            "maxlength": "",
            "readonly": 0,
            "disabled": 0
        },
        {
            "key": "field_5092f9179cb0e",
            "label": "Instagram Username",
            "name": "libtech_team_instagram_username",
            "type": "text",
            "instructions": "",
            "required": 0,
            "conditional_logic": 0,
            "wrapper": {
                "width": "",
                "class": "",
                "id": ""
            },
            "default_value": "",
            "placeholder": "",
            "prepend": "",
            "append": "",
            "formatting": "none",
            "maxlength": "",
            "readonly": 0,
            "disabled": 0
        },
        {
            "key": "field_528c066e055c5",
            "label": "Gallery",
            "name": "libtech_team_gallery",
            "type": "wysiwyg",
            "instructions": "",
            "required": 0,
            "conditional_logic": 0,
            "wrapper": {
                "width": "",
                "class": "",
                "id": ""
            },
            "default_value": "",
            "toolbar": "full",
            "media_upload": 1,
            "tabs": "all"
        },
        {
            "key": "field_5092f917a4cc4",
            "label": "Questions and Answers",
            "name": "libtech_team_q_and_a",
            "type": "wysiwyg",
            "instructions": "",
            "required": 0,
            "conditional_logic": 0,
            "wrapper": {
                "width": "",
                "class": "",
                "id": ""
            },
            "default_value": "",
            "toolbar": "full",
            "media_upload": 0,
            "tabs": "all"
        }
    ],
    "location": [
        [
            {
                "param": "post_type",
                "operator": "==",
                "value": "libtech_team_snow"
            }
        ],
        [
            {
                "param": "post_type",
                "operator": "==",
                "value": "libtech_team_nas"
            }
        ],
        [
            {
                "param": "post_type",
                "operator": "==",
                "value": "libtech_team_surf"
            }
        ],
        [
            {
                "param": "post_type",
                "operator": "==",
                "value": "libtech_team_skate"
            }
        ]
    ],
    "menu_order": 0,
    "position": "normal",
    "style": "default",
    "label_placement": "top",
    "instruction_placement": "label",
    "hide_on_screen": "",
    "modified": 1432675628,
    "local": "json"
}